[{"id":"tribute-phavJrol","date":"2018-01-26T23:31:18.408Z","caption":"BARONRIES FOR THE BARONRY GOD","postedToGit":true,"htmlFragment":"<li class=\"pane\">\n  <div class=\"time-stamp entry-meta\">\n    <a href=\"tribute-phavJrol.html\">\n      <time datetime=\"2018-01-26T23:31:18.408Z\">2018-1-26 18:31:18</time>\n    </a>\n  </div><div class=\"text-caption\">BARONRIES FOR THE BARONRY GOD</div>\n</li>","postedSingleVideoPage":true},{"id":"tribute-PrPHXHec","date":"2018-01-27T01:36:16.367Z","caption":"RUDEBOYS FOR THE RUDEBOY GOD","postedToGit":true,"htmlFragment":"<li class=\"pane\">\n  <div class=\"time-stamp entry-meta\">\n    <a href=\"tribute-PrPHXHec.html\">\n      <time datetime=\"2018-01-27T01:36:16.367Z\">2018-1-26 20:36:16</time>\n    </a>\n  </div><div class=\"text-caption\">RUDEBOYS FOR THE RUDEBOY GOD</div>\n</li>","postedSingleVideoPage":true},{"id":"tribute-lKHRhLxr","date":"2018-01-27T02:00:04.071Z","caption":"PTARMIGANS FOR THE PTARMIGAN THRONE! MOORGAMES FOR THE MOORGAME CORPORATION","postedToGit":true,"htmlFragment":"<li class=\"pane\">\n  <div class=\"time-stamp entry-meta\">\n    <a href=\"tribute-lKHRhLxr.html\">\n      <time datetime=\"2018-01-27T02:00:04.071Z\">2018-1-26 21:00:04</time>\n    </a>\n  </div><div class=\"text-caption\">PTARMIGANS FOR THE PTARMIGAN THRONE! MOORGAMES FOR THE MOORGAME CORPORATION</div>\n</li>","postedSingleVideoPage":true},{"id":"tribute-UcnkbQGV","date":"2018-01-27T05:00:04.508Z","caption":"LUCES FOR THE LUCE GOD! DRAMATISTS FOR THE DRAMATIST BLOB","postedToGit":true,"htmlFragment":"<li class=\"pane\">\n  <div class=\"time-stamp entry-meta\">\n    <a href=\"tribute-UcnkbQGV.html\">\n      <time datetime=\"2018-01-27T05:00:04.508Z\">2018-1-27 00:00:04</time>\n    </a>\n  </div><div class=\"text-caption\">LUCES FOR THE LUCE GOD! DRAMATISTS FOR THE DRAMATIST BLOB</div>\n</li>","postedSingleVideoPage":true},{"id":"tribute-odaEReMY","date":"2018-01-27T08:00:04.811Z","caption":"CAUTIONS FOR THE CAUTION LORD! CAUTIOUS OPTIMISMS FOR THE CAUTIOUS OPTIMISM THRONE","postedToGit":true,"htmlFragment":"<li class=\"pane\">\n  <div class=\"time-stamp entry-meta\">\n    <a href=\"tribute-odaEReMY.html\">\n      <time datetime=\"2018-01-27T08:00:04.811Z\">2018-1-27 03:00:04</time>\n    </a>\n  </div><div class=\"text-caption\">CAUTIONS FOR THE CAUTION LORD! CAUTIOUS OPTIMISMS FOR THE CAUTIOUS OPTIMISM THRONE</div>\n</li>","postedSingleVideoPage":true},{"id":"tribute-UQpkgcaR","date":"2018-01-27T10:00:03.714Z","caption":"SPITTERS FOR THE SPITTER GOD! CROWBARS FOR THE CROWBAR QUEEN","postedToGit":true,"htmlFragment":"<li class=\"pane\">\n  <div class=\"time-stamp entry-meta\">\n    <a href=\"tribute-UQpkgcaR.html\">\n      <time datetime=\"2018-01-27T10:00:03.714Z\">2018-1-27 05:00:03</time>\n    </a>\n  </div><div class=\"text-caption\">SPITTERS FOR THE SPITTER GOD! CROWBARS FOR THE CROWBAR QUEEN</div>\n</li>","postedSingleVideoPage":true},{"id":"tribute-TWyKjmrb","date":"2018-01-27T13:00:05.552Z","caption":"TOXOPHILITES FOR THE TOXOPHILITE LORD","postedToGit":true,"htmlFragment":"<li class=\"pane\">\n  <div class=\"time-stamp entry-meta\">\n    <a href=\"tribute-TWyKjmrb.html\">\n      <time datetime=\"2018-01-27T13:00:05.552Z\">2018-1-27 08:00:05</time>\n    </a>\n  </div><div class=\"text-caption\">TOXOPHILITES FOR THE TOXOPHILITE LORD</div>\n</li>","postedSingleVideoPage":true},{"id":"tribute-NOIWmqYI","date":"2018-01-27T17:00:04.096Z","caption":"WIELDERS FOR THE WIELDER GOD! ARCHMAGES UNTO THE ARCHMAGE FIEND","postedToGit":true,"htmlFragment":"<li class=\"pane\">\n  <div class=\"time-stamp entry-meta\">\n    <a href=\"tribute-NOIWmqYI.html\">\n      <time datetime=\"2018-01-27T17:00:04.096Z\">2018-1-27 12:00:04</time>\n    </a>\n  </div><div class=\"text-caption\">WIELDERS FOR THE WIELDER GOD! ARCHMAGES UNTO THE ARCHMAGE FIEND</div>\n</li>","postedSingleVideoPage":true},{"id":"tribute-VJhvRBPy","date":"2018-01-27T20:00:03.418Z","caption":"ASININITIES FOR THE ASININITY GOD! PUERILITIES FOR THE PUERILITY DIMENSION","postedToGit":true,"htmlFragment":"<li class=\"pane\">\n  <div class=\"time-stamp entry-meta\">\n    <a href=\"tribute-VJhvRBPy.html\">\n      <time datetime=\"2018-01-27T20:00:03.418Z\">2018-1-27 15:00:03</time>\n    </a>\n  </div><div class=\"text-caption\">ASININITIES FOR THE ASININITY GOD! PUERILITIES FOR THE PUERILITY DIMENSION</div>\n</li>","postedSingleVideoPage":true},{"id":"tribute-dCGPZiJV","date":"2018-01-27T23:00:04.762Z","caption":"CHARISMAS FOR THE CHARISMA GOD! GRAVITA FOR THE GRAVITUM THRONE","postedToGit":true,"htmlFragment":"<li class=\"pane\">\n  <div class=\"time-stamp entry-meta\">\n    <a href=\"tribute-dCGPZiJV.html\">\n      <time datetime=\"2018-01-27T23:00:04.762Z\">2018-1-27 18:00:04</time>\n    </a>\n  </div><div class=\"text-caption\">CHARISMAS FOR THE CHARISMA GOD! GRAVITA FOR THE GRAVITUM THRONE</div>\n</li>","postedSingleVideoPage":true},{"id":"tribute-JsyGTWEb","date":"2018-01-28T02:00:03.269Z","caption":"ABANDONING FOR THE ABANDONING GOD! FAILING FOR THE FAILING LORD","postedToGit":true,"htmlFragment":"<li class=\"pane\">\n  <div class=\"time-stamp entry-meta\">\n    <a href=\"tribute-JsyGTWEb.html\">\n      <time datetime=\"2018-01-28T02:00:03.269Z\">2018-1-27 21:00:03</time>\n    </a>\n  </div><div class=\"text-caption\">ABANDONING FOR THE ABANDONING GOD! FAILING FOR THE FAILING LORD</div>\n</li>","postedSingleVideoPage":true},{"id":"tribute-rzNihcGG","date":"2018-01-28T05:00:04.910Z","caption":"SIGNORAS FOR THE SIGNORA GOD! DE L' AMOURS FOR THE DE L' AMOUR LORD","postedToGit":true,"htmlFragment":"<li class=\"pane\">\n  <div class=\"time-stamp entry-meta\">\n    <a href=\"tribute-rzNihcGG.html\">\n      <time datetime=\"2018-01-28T05:00:04.910Z\">2018-1-28 00:00:04</time>\n    </a>\n  </div><div class=\"text-caption\">SIGNORAS FOR THE SIGNORA GOD! DE L' AMOURS FOR THE DE L' AMOUR LORD</div>\n</li>","postedSingleVideoPage":true},{"id":"tribute-YasfNPHf","date":"2018-01-28T08:00:04.242Z","caption":"YACKETY-YAKS FOR THE YACKETY-YAK GOD","postedToGit":true,"htmlFragment":"<li class=\"pane\">\n  <div class=\"time-stamp entry-meta\">\n    <a href=\"tribute-YasfNPHf.html\">\n      <time datetime=\"2018-01-28T08:00:04.242Z\">2018-1-28 03:00:04</time>\n    </a>\n  </div><div class=\"text-caption\">YACKETY-YAKS FOR THE YACKETY-YAK GOD</div>\n</li>","postedSingleVideoPage":true},{"id":"tribute-XtxypYbu","date":"2018-01-28T13:00:05.953Z","caption":"EDUCATIONALISTS FOR THE EDUCATIONALIST GOD! ERUDITE SCHOLARS FOR THE ERUDITE SCHOLAR POTENTATE","postedToGit":true,"htmlFragment":"<li class=\"pane\">\n  <div class=\"time-stamp entry-meta\">\n    <a href=\"tribute-XtxypYbu.html\">\n      <time datetime=\"2018-01-28T13:00:05.953Z\">2018-1-28 08:00:05</time>\n    </a>\n  </div><div class=\"text-caption\">EDUCATIONALISTS FOR THE EDUCATIONALIST GOD! ERUDITE SCHOLARS FOR THE ERUDITE SCHOLAR POTENTATE</div>\n</li>","postedSingleVideoPage":true},{"id":"tribute-rgGUVlgJ","date":"2018-01-28T17:00:02.942Z","caption":"ORMANDIES FOR THE ORMANDY GOD","postedToGit":true,"htmlFragment":"<li class=\"pane\">\n  <div class=\"time-stamp entry-meta\">\n    <a href=\"tribute-rgGUVlgJ.html\">\n      <time datetime=\"2018-01-28T17:00:02.942Z\">2018-1-28 12:00:02</time>\n    </a>\n  </div><div class=\"text-caption\">ORMANDIES FOR THE ORMANDY GOD</div>\n</li>","postedSingleVideoPage":true},{"id":"tribute-HQMdMRBm","date":"2018-01-28T20:00:03.310Z","caption":"AIRCHECKS UNTO THE AIRCHECK GOD","postedToGit":true,"htmlFragment":"<li class=\"pane\">\n  <div class=\"time-stamp entry-meta\">\n    <a href=\"tribute-HQMdMRBm.html\">\n      <time datetime=\"2018-01-28T20:00:03.310Z\">2018-1-28 15:00:03</time>\n    </a>\n  </div><div class=\"text-caption\">AIRCHECKS UNTO THE AIRCHECK GOD</div>\n</li>","postedSingleVideoPage":true},{"id":"tribute-fPPrfMIR","date":"2018-01-28T23:00:05.270Z","caption":"ADVISING FOR THE ADVISING GOD! HOTFIXES FOR THE HOTFIX SALAD","postedToGit":true,"htmlFragment":"<li class=\"pane\">\n  <div class=\"time-stamp entry-meta\">\n    <a href=\"tribute-fPPrfMIR.html\">\n      <time datetime=\"2018-01-28T23:00:05.270Z\">2018-1-28 18:00:05</time>\n    </a>\n  </div><div class=\"text-caption\">ADVISING FOR THE ADVISING GOD! HOTFIXES FOR THE HOTFIX SALAD</div>\n</li>","postedSingleVideoPage":true},{"id":"tribute-lpZrOjoy","date":"2018-01-29T02:00:02.888Z","caption":"DEXFENFLURAMINES FOR THE DEXFENFLURAMINE GOD! FENFLURAMINES FOR THE FENFLURAMINE QUEEN","postedToGit":true,"htmlFragment":"<li class=\"pane\">\n  <div class=\"time-stamp entry-meta\">\n    <a href=\"tribute-lpZrOjoy.html\">\n      <time datetime=\"2018-01-29T02:00:02.888Z\">2018-1-28 21:00:02</time>\n    </a>\n  </div><div class=\"text-caption\">DEXFENFLURAMINES FOR THE DEXFENFLURAMINE GOD! FENFLURAMINES FOR THE FENFLURAMINE QUEEN</div>\n</li>","postedSingleVideoPage":true},{"id":"tribute-SPSiAJJQ","date":"2018-01-29T05:00:03.966Z","caption":"CAPITULATIONS FOR THE CAPITULATION GOD! DÉBÂCLES FOR THE DÉBÂCLE PRESIDENT","postedToGit":true,"htmlFragment":"<li class=\"pane\">\n  <div class=\"time-stamp entry-meta\">\n    <a href=\"tribute-SPSiAJJQ.html\">\n      <time datetime=\"2018-01-29T05:00:03.966Z\">2018-1-29 00:00:03</time>\n    </a>\n  </div><div class=\"text-caption\">CAPITULATIONS FOR THE CAPITULATION GOD! DÉBÂCLES FOR THE DÉBÂCLE PRESIDENT</div>\n</li>","postedSingleVideoPage":true},{"id":"tribute-DAHdkYiH","date":"2018-01-29T08:00:04.672Z","caption":"OBSCENITIES FOR THE OBSCENITY QUEEN! IMPROPRIETIES FOR THE IMPROPRIETY MONSTER","postedToGit":true,"htmlFragment":"<li class=\"pane\">\n  <div class=\"time-stamp entry-meta\">\n    <a href=\"tribute-DAHdkYiH.html\">\n      <time datetime=\"2018-01-29T08:00:04.672Z\">2018-1-29 03:00:04</time>\n    </a>\n  </div><div class=\"text-caption\">OBSCENITIES FOR THE OBSCENITY QUEEN! IMPROPRIETIES FOR THE IMPROPRIETY MONSTER</div>\n</li>","postedSingleVideoPage":true}]