[{"id":"tribute-bAkooMER","date":"2018-07-13T07:00:04.750Z","caption":"IMPALA FOR THE IMPALA GOD! ANTELOPES FOR THE ANTELOPE TREE","postedToGit":true,"htmlFragment":"<li class=\"pane\">\n  <div class=\"time-stamp entry-meta\">\n    <a href=\"tribute-bAkooMER.html\">\n      <time datetime=\"2018-07-13T07:00:04.750Z\">2018-7-13 03:00:04</time>\n    </a>\n  </div><div class=\"text-caption\">IMPALA FOR THE IMPALA GOD! ANTELOPES FOR THE ANTELOPE TREE</div>\n</li>","postedSingleVideoPage":true},{"id":"tribute-BGCriBHP","date":"2018-07-13T09:00:03.063Z","caption":"CLARIFIERS FOR THE CLARIFIER GOD! PRESSURIZERS FOR THE PRESSURIZER BLOB","postedToGit":true,"htmlFragment":"<li class=\"pane\">\n  <div class=\"time-stamp entry-meta\">\n    <a href=\"tribute-BGCriBHP.html\">\n      <time datetime=\"2018-07-13T09:00:03.063Z\">2018-7-13 05:00:03</time>\n    </a>\n  </div><div class=\"text-caption\">CLARIFIERS FOR THE CLARIFIER GOD! PRESSURIZERS FOR THE PRESSURIZER BLOB</div>\n</li>","postedSingleVideoPage":true},{"id":"tribute-flTVPKDd","date":"2018-07-13T12:00:05.793Z","caption":"STYLIS FOR THE STYLI THRONE! OFFSCOURING FOR THE OFFSCOURING QUEEN","postedToGit":true,"htmlFragment":"<li class=\"pane\">\n  <div class=\"time-stamp entry-meta\">\n    <a href=\"tribute-flTVPKDd.html\">\n      <time datetime=\"2018-07-13T12:00:05.793Z\">2018-7-13 08:00:05</time>\n    </a>\n  </div><div class=\"text-caption\">STYLIS FOR THE STYLI THRONE! OFFSCOURING FOR THE OFFSCOURING QUEEN</div>\n</li>","postedSingleVideoPage":true},{"id":"tribute-RrbrEAnf","date":"2018-07-13T16:00:02.788Z","caption":"WOOFERS FOR THE WOOFER PRESIDENT! CYLINDRICAL TUBES UNTO THE CYLINDRICAL TUBE GODDESS","postedToGit":true,"htmlFragment":"<li class=\"pane\">\n  <div class=\"time-stamp entry-meta\">\n    <a href=\"tribute-RrbrEAnf.html\">\n      <time datetime=\"2018-07-13T16:00:02.788Z\">2018-7-13 12:00:02</time>\n    </a>\n  </div><div class=\"text-caption\">WOOFERS FOR THE WOOFER PRESIDENT! CYLINDRICAL TUBES UNTO THE CYLINDRICAL TUBE GODDESS</div>\n</li>","postedSingleVideoPage":true}]